README.md
setup.py
nyuclassesdl/__init__.py
nyuclassesdl/__main__.py
nyuclassesdl/nyuclassesdl.py
nyuclassesdl.egg-info/PKG-INFO
nyuclassesdl.egg-info/SOURCES.txt
nyuclassesdl.egg-info/dependency_links.txt
nyuclassesdl.egg-info/entry_points.txt
nyuclassesdl.egg-info/requires.txt
nyuclassesdl.egg-info/top_level.txt