Metadata-Version: 1.1
Name: nyuclassesdl
Version: 1.0.5
Summary: a python library for automatically downloading files from NYU Classes
Home-page: https://github.com/zhiaozhou/nyuclassesdl
Author: Zhiao Zhou
Author-email: zz1749@nyu.edu
License: UNKNOWN
Keywords: nyu nyuclasses
Platform: UNKNOWN
Classifier: Development Status :: 3 - Alpha
Classifier: Intended Audience :: Education
Classifier: Topic :: Utilities
Classifier: License :: OSI Approved :: MIT License
Classifier: Programming Language :: Python :: 2
Classifier: Programming Language :: Python :: 2.7
Classifier: Programming Language :: Python :: 3
Classifier: Programming Language :: Python :: 3.4
Classifier: Programming Language :: Python :: 3.5
Classifier: Programming Language :: Python :: 3.6
Classifier: Operating System :: Unix
Classifier: Operating System :: POSIX
Classifier: Operating System :: Microsoft :: Windows
Classifier: Operating System :: MacOS
